edgefedsim/application.py
edgefedsim/infrastructure.py
edgefedsim/scheduler.py
edgefedsim/simulation.py
edgefedsim/utils.py
edgefedsim/schedulers/abstract_scheduler.py
edgefedsim-0.1.0.dist-info/METADATA
edgefedsim-0.1.0.dist-info/WHEEL
edgefedsim-0.1.0.dist-info/top_level.txt
edgefedsim-0.1.0.dist-info/RECORD
