Metadata-Version: 2.4
Name: edgefedsim
Version: 0.1.0
Summary: A simulator for federated learning in edge-cloud environments.
Author-email: Hossein Ahmadpanah <h.ahmadpanah@iau.ac.ir>
Project-URL: Homepage, https://github.com/ahmadpanah/EdgeFedSim
Project-URL: Issues, https://github.com/ahmadpanah/EdgeFedSim/issues
Classifier: Programming Language :: Python :: 3
Classifier: Operating System :: OS Independent
Classifier: Topic :: Scientific/Engineering
Classifier: Topic :: System :: Distributed Computing
Requires-Python: >=3.8
Requires-Dist: simpy==4.0.1
Requires-Dist: networkx==2.8.8
Requires-Dist: numpy>=1.26.0
Requires-Dist: python-louvain==0.16
Requires-Dist: tabulate==0.9.0
Requires-Dist: pyyaml
